opentelemetry/instrumentation/alephalpha/__init__.py
opentelemetry/instrumentation/alephalpha/config.py
opentelemetry/instrumentation/alephalpha/event_emitter.py
opentelemetry/instrumentation/alephalpha/event_models.py
opentelemetry/instrumentation/alephalpha/span_utils.py
opentelemetry/instrumentation/alephalpha/utils.py
opentelemetry/instrumentation/alephalpha/version.py
opentelemetry_instrumentation_alephalpha-0.51.1.dist-info/METADATA
opentelemetry_instrumentation_alephalpha-0.51.1.dist-info/WHEEL
opentelemetry_instrumentation_alephalpha-0.51.1.dist-info/entry_points.txt
opentelemetry_instrumentation_alephalpha-0.51.1.dist-info/RECORD
