Metadata-Version: 2.4
Name: opentelemetry-instrumentation-alephalpha
Version: 0.51.1
Summary: OpenTelemetry Aleph Alpha instrumentation
Project-URL: Repository, https://github.com/traceloop/openllmetry/tree/main/packages/opentelemetry-instrumentation-alephalpha
Author-email: Gal Kleinman <gal@traceloop.com>, Nir Gazit <nir@traceloop.com>, Benedikt Wolf <bene25@web.de>
License-Expression: Apache-2.0
Requires-Python: <4,>=3.10
Requires-Dist: opentelemetry-api<2,>=1.38.0
Requires-Dist: opentelemetry-instrumentation>=0.59b0
Requires-Dist: opentelemetry-semantic-conventions-ai<0.5.0,>=0.4.13
Requires-Dist: opentelemetry-semantic-conventions>=0.59b0
Provides-Extra: instruments
Requires-Dist: aleph-alpha-client; extra == 'instruments'
